{"connector": {"id": "KnAccount", "group": "Financiële Inrichting", "description": "Grootboekrekening", "methods": ["POST", "PUT", "DELETE"]}, "schemas": [{"connector_id": "KnAccount", "method": "POST", "language": "nl", "group": "Financiële Inrichting", "schema": {"type": "object", "properties": {"KnAccount": {"type": "object", "properties": {"Element": {"type": "object", "properties": {"Fields": {"type": "object", "properties": {"AcNr": {"type": "string", "maxLength": 16, "description": "Rekeningnummer", "format": ""}, "Ds": {"type": "string", "maxLength": 50, "description": "Omschrijving", "format": ""}, "Ds_1031": {"type": "string", "maxLength": 50, "description": "Omschrijving (Duits)", "format": ""}, "Ds_1036": {"type": "string", "maxLength": 50, "description": "Omschrijving (Frans)", "format": ""}, "Ds_1043": {"type": "string", "maxLength": 50, "description": "Omschrijving (Nederlands)", "format": ""}, "Ds_2057": {"type": "string", "maxLength": 50, "description": "Omschrijving (Engels)", "format": ""}, "Ds_2067": {"type": "string", "maxLength": 50, "description": "Omschrijving (Vlaams)", "format": ""}, "SeNm": {"type": "string", "maxLength": 10, "description": "Zoeknaam", "format": ""}, "SaYn": {"type": "boolean", "description": "Verzamelrekening", "format": ""}, "FaYn": {"type": "boolean", "description": "Afletterbaar", "format": ""}, "Bl": {"type": "boolean", "description": "Geblokkeerd", "format": ""}, "VaAt": {"type": "string", "enum": ["1", "2", "3", "4"], "maxLength": 20, "description": "Type rekening\n1 = Activa;\n2 = Passiva;\n3 = Opbrengsten;\n4 = Kosten;", "format": ""}, "VaPc": {"type": "string", "enum": ["G", "D", "I", "B", "O", "GD"], "maxLength": 20, "description": "Soort rekening\nG = Goederen;\nD = Diensten;\nI = Investeringen;\nB = Btw;\nO = Overige;\nGD = Goederen en diensten;", "format": ""}, "VaDc": {"type": "string", "enum": ["N", "D", "C"], "maxLength": 20, "description": "Voorkeur (debet/credit)\nN = Geen voorkeur;\nD = Debet;\nC = Credit;", "format": ""}, "VaYn": {"type": "boolean", "description": "Btw toestaan", "format": ""}, "VaCo": {"type": "string", "maxLength": 3, "description": "Voorkeur btw-code", "format": ""}, "CaYn": {"type": "boolean", "description": "In valuta", "format": ""}, "CuCo": {"type": "string", "maxLength": 3, "description": "Valuta", "format": ""}, "VaA1": {"type": "string", "enum": ["N", "B", "P"], "maxLength": 20, "description": "Verbijzonderingsas 1\nN = Niet verbijzonderen;\nB = Handmatig bij boeking (op bedrag);\nP = Automatisch (percentueel);", "format": ""}, "VaA2": {"type": "string", "enum": ["N", "B", "P"], "maxLength": 20, "description": "Verbijzonderingsas 2\nN = Niet verbijzonderen;\nB = Handmatig bij boeking (op bedrag);\nP = Automatisch (percentueel);", "format": ""}, "VaA3": {"type": "string", "enum": ["N", "B", "P"], "maxLength": 20, "description": "Verbijzonderingsas 3\nN = Niet verbijzonderen;\nB = Handmatig bij boeking (op bedrag);\nP = Automatisch (percentueel);", "format": ""}, "VaA4": {"type": "string", "enum": ["N", "B", "P"], "maxLength": 20, "description": "Verbijzonderingsas 4\nN = Niet verbijzonderen;\nB = Handmatig bij boeking (op bedrag);\nP = Automatisch (percentueel);", "format": ""}, "VaA5": {"type": "string", "enum": ["N", "B", "P"], "maxLength": 20, "description": "Verbijzonderingsas 5\nN = Niet verbijzonderen;\nB = Handmatig bij boeking (op bedrag);\nP = Automatisch (percentueel);", "format": ""}, "VaPp": {"type": "string", "enum": ["N", "T", "V", "I"], "maxLength": 20, "description": "Doorboeken projecten\nN = Geen projectboeking;\nT = Projectboeking toegestaan;\nV = Projectboeking verplicht;\nI = Investeringsproject verplicht;", "format": ""}, "AcMm": {"type": "string", "description": "Memo", "format": "byte"}, "CoAc": {"type": "string", "enum": ["N", "D", "C", "G"], "maxLength": 20, "description": "Type verzamelrekening\nN = Geen verzamelrekening;\nD = Debiteur;\nC = Crediteur;\nG = Grootboek;", "format": ""}, "ColA": {"type": "string", "maxLength": 16, "description": "Verzamelen op", "format": ""}, "PeDi": {"type": "integer", "description": "Periodeverdeeltabel", "format": ""}, "VaBu": {"type": "string", "enum": ["N", "B", "BA", "A"], "maxLength": 20, "description": "Budgetteren\nN = Niet van toepassing;\nB = Bedrag;\nBA = Bedrag + aantal;\nA = Aantal;", "format": ""}, "LiAc": {"type": "string", "maxLength": 16, "description": "Afletteren met", "format": ""}, "BaAc": {"type": "string", "maxLength": 16, "description": "Afwijkende balansrekening", "format": ""}, "VaEx": {"type": "string", "enum": ["R", "B"], "maxLength": 20, "description": "Te tonen in exploitatie\nR = Realisatie;\nB = Budget;", "format": ""}, "CmYN": {"type": "boolean", "description": "Verdichten", "format": ""}, "FaAl": {"type": "boolean", "description": "Activa toevoegen bij boeken inkoop/bank", "format": ""}, "CmMa": {"type": "boolean", "description": "Verplichting bij inkoopboeking verplicht", "format": ""}, "MaBl": {"type": "boolean", "description": "Handmatig boeken blokkeren", "format": ""}, "FeId": {"type": "string", "maxLength": 12, "description": "Rapportagecockpit", "format": ""}, "Ref": {"type": "string", "maxLength": 32, "description": "RGS-referentiecode", "format": ""}, "RfEx": {"type": "string", "maxLength": 32, "description": "RGS-extensie", "format": ""}, "DsId": {"type": "integer", "description": "Aanmaningsset", "format": ""}}, "required": ["AcNr"]}}}}}}}, "source_file": "profit/nl/Financiële Inrichting.json"}, {"connector_id": "KnAccount", "method": "PUT", "language": "nl", "group": "Financiële Inrichting", "schema": {"type": "object", "properties": {"KnAccount": {"type": "object", "properties": {"Element": {"type": "object", "properties": {"Fields": {"type": "object", "properties": {"AcNr": {"type": "string", "maxLength": 16, "description": "Rekeningnummer", "format": ""}, "Ds": {"type": "string", "maxLength": 50, "description": "Omschrijving", "format": ""}, "Ds_1031": {"type": "string", "maxLength": 50, "description": "Omschrijving (Duits)", "format": ""}, "Ds_1036": {"type": "string", "maxLength": 50, "description": "Omschrijving (Frans)", "format": ""}, "Ds_1043": {"type": "string", "maxLength": 50, "description": "Omschrijving (Nederlands)", "format": ""}, "Ds_2057": {"type": "string", "maxLength": 50, "description": "Omschrijving (Engels)", "format": ""}, "Ds_2067": {"type": "string", "maxLength": 50, "description": "Omschrijving (Vlaams)", "format": ""}, "SeNm": {"type": "string", "maxLength": 10, "description": "Zoeknaam", "format": ""}, "SaYn": {"type": "boolean", "description": "Verzamelrekening", "format": ""}, "FaYn": {"type": "boolean", "description": "Afletterbaar", "format": ""}, "Bl": {"type": "boolean", "description": "Geblokkeerd", "format": ""}, "VaAt": {"type": "string", "enum": ["1", "2", "3", "4"], "maxLength": 20, "description": "Type rekening\n1 = Activa;\n2 = Passiva;\n3 = Opbrengsten;\n4 = Kosten;", "format": ""}, "VaPc": {"type": "string", "enum": ["G", "D", "I", "B", "O", "GD"], "maxLength": 20, "description": "Soort rekening\nG = Goederen;\nD = Diensten;\nI = Investeringen;\nB = Btw;\nO = Overige;\nGD = Goederen en diensten;", "format": ""}, "VaDc": {"type": "string", "enum": ["N", "D", "C"], "maxLength": 20, "description": "Voorkeur (debet/credit)\nN = Geen voorkeur;\nD = Debet;\nC = Credit;", "format": ""}, "VaYn": {"type": "boolean", "description": "Btw toestaan", "format": ""}, "VaCo": {"type": "string", "maxLength": 3, "description": "Voorkeur btw-code", "format": ""}, "CaYn": {"type": "boolean", "description": "In valuta", "format": ""}, "CuCo": {"type": "string", "maxLength": 3, "description": "Valuta", "format": ""}, "VaA1": {"type": "string", "enum": ["N", "B", "P"], "maxLength": 20, "description": "Verbijzonderingsas 1\nN = Niet verbijzonderen;\nB = Handmatig bij boeking (op bedrag);\nP = Automatisch (percentueel);", "format": ""}, "VaA2": {"type": "string", "enum": ["N", "B", "P"], "maxLength": 20, "description": "Verbijzonderingsas 2\nN = Niet verbijzonderen;\nB = Handmatig bij boeking (op bedrag);\nP = Automatisch (percentueel);", "format": ""}, "VaA3": {"type": "string", "enum": ["N", "B", "P"], "maxLength": 20, "description": "Verbijzonderingsas 3\nN = Niet verbijzonderen;\nB = Handmatig bij boeking (op bedrag);\nP = Automatisch (percentueel);", "format": ""}, "VaA4": {"type": "string", "enum": ["N", "B", "P"], "maxLength": 20, "description": "Verbijzonderingsas 4\nN = Niet verbijzonderen;\nB = Handmatig bij boeking (op bedrag);\nP = Automatisch (percentueel);", "format": ""}, "VaA5": {"type": "string", "enum": ["N", "B", "P"], "maxLength": 20, "description": "Verbijzonderingsas 5\nN = Niet verbijzonderen;\nB = Handmatig bij boeking (op bedrag);\nP = Automatisch (percentueel);", "format": ""}, "VaPp": {"type": "string", "enum": ["N", "T", "V", "I"], "maxLength": 20, "description": "Doorboeken projecten\nN = Geen projectboeking;\nT = Projectboeking toegestaan;\nV = Projectboeking verplicht;\nI = Investeringsproject verplicht;", "format": ""}, "AcMm": {"type": "string", "description": "Memo", "format": "byte"}, "CoAc": {"type": "string", "enum": ["N", "D", "C", "G"], "maxLength": 20, "description": "Type verzamelrekening\nN = Geen verzamelrekening;\nD = Debiteur;\nC = Crediteur;\nG = Grootboek;", "format": ""}, "ColA": {"type": "string", "maxLength": 16, "description": "Verzamelen op", "format": ""}, "PeDi": {"type": "integer", "description": "Periodeverdeeltabel", "format": ""}, "VaBu": {"type": "string", "enum": ["N", "B", "BA", "A"], "maxLength": 20, "description": "Budgetteren\nN = Niet van toepassing;\nB = Bedrag;\nBA = Bedrag + aantal;\nA = Aantal;", "format": ""}, "LiAc": {"type": "string", "maxLength": 16, "description": "Afletteren met", "format": ""}, "BaAc": {"type": "string", "maxLength": 16, "description": "Afwijkende balansrekening", "format": ""}, "VaEx": {"type": "string", "enum": ["R", "B"], "maxLength": 20, "description": "Te tonen in exploitatie\nR = Realisatie;\nB = Budget;", "format": ""}, "CmYN": {"type": "boolean", "description": "Verdichten", "format": ""}, "FaAl": {"type": "boolean", "description": "Activa toevoegen bij boeken inkoop/bank", "format": ""}, "CmMa": {"type": "boolean", "description": "Verplichting bij inkoopboeking verplicht", "format": ""}, "MaBl": {"type": "boolean", "description": "Handmatig boeken blokkeren", "format": ""}, "FeId": {"type": "string", "maxLength": 12, "description": "Rapportagecockpit", "format": ""}, "Ref": {"type": "string", "maxLength": 32, "description": "RGS-referentiecode", "format": ""}, "RfEx": {"type": "string", "maxLength": 32, "description": "RGS-extensie", "format": ""}, "DsId": {"type": "integer", "description": "Aanmaningsset", "format": ""}}, "required": ["AcNr"]}}}}}}}, "source_file": "profit/nl/Financiële Inrichting.json"}], "examples": [{"connector_id": "KnAccount", "name": "basis", "method_hint": "POST", "relative_path": "post/basis.json", "payload": {"KnAccount": {"Element": {"Fields": {"AcNr": "1605", "Ds": "Crediteuren buitenland", "SeNm": "CreB", "SaYn": false, "FaYn": false, "VaAt": "2", "VaPc": "GD", "VaDc": "C", "VaYn": true, "VaCo": "4", "CaYn": false}}}}}]}